afpropred/blast_binaries/linux/psiblast
afpropred/blast_binaries/mac/psiblast
afpropred/blast_binaries/windows/ncbi-vdb-md.dll
afpropred/blast_binaries/windows/nghttp2.dll
afpropred/blast_binaries/windows/psiblast.exe
afpropred/possum/featureGenerator.py
afpropred/possum/headerHandler.py
afpropred/possum/matrixTransformer.py
afpropred/possum/possum.py
afpropred/possum/possum_ft.py
afpropred/python_scripts/__init__.py
afpropred/python_scripts/afpropred.py
afpropred-1.1.dist-info/LICENSE
afpropred-1.1.dist-info/METADATA
afpropred-1.1.dist-info/WHEEL
afpropred-1.1.dist-info/entry_points.txt
afpropred-1.1.dist-info/top_level.txt
afpropred-1.1.dist-info/RECORD
