Metadata-Version: 2.1
Name: afpropred
Version: 1.1
Summary: A tool to predict anti-freezing proteins
Home-page: https://github.com/raghavagps/afpropred
Requires-Python: >=3.8
License-File: LICENSE
Requires-Dist: numpy
Requires-Dist: pandas
Requires-Dist: scikit-learn >=1.3.0
Requires-Dist: argparse
Requires-Dist: biopython
Requires-Dist: requests
